asciidoxy/__init__.py
asciidoxy/_version.py
asciidoxy/api_reference.py
asciidoxy/asciidoctor.py
asciidoxy/cli.py
asciidoxy/compat.py
asciidoxy/config.py
asciidoxy/document.py
asciidoxy/model.py
asciidoxy/path_utils.py
asciidoxy/generator/__init__.py
asciidoxy/generator/asciidoc.py
asciidoxy/generator/asciidoxy-no-toc.css
asciidoxy/generator/asciidoxy-toc-left.css
asciidoxy/generator/asciidoxy-toc-right.css
asciidoxy/generator/cache.py
asciidoxy/generator/context.py
asciidoxy/generator/errors.py
asciidoxy/generator/filters.py
asciidoxy/generator/navigation.py
asciidoxy/generator/templates/__init__.py
asciidoxy/generator/templates/helpers.py
asciidoxy/generator/templates/cpp/__init__.py
asciidoxy/generator/templates/cpp/_function.mako
asciidoxy/generator/templates/cpp/alias.mako
asciidoxy/generator/templates/cpp/class.mako
asciidoxy/generator/templates/cpp/enum.mako
asciidoxy/generator/templates/cpp/function.mako
asciidoxy/generator/templates/cpp/helpers.py
asciidoxy/generator/templates/cpp/interface.mako
asciidoxy/generator/templates/cpp/method.mako
asciidoxy/generator/templates/cpp/struct.mako
asciidoxy/generator/templates/cpp/typedef.mako
asciidoxy/generator/templates/java/__init__.py
asciidoxy/generator/templates/java/class.mako
asciidoxy/generator/templates/java/enum.mako
asciidoxy/generator/templates/java/helpers.py
asciidoxy/generator/templates/java/interface.mako
asciidoxy/generator/templates/java/method.mako
asciidoxy/generator/templates/kotlin/__init__.py
asciidoxy/generator/templates/kotlin/class.mako
asciidoxy/generator/templates/kotlin/enum.mako
asciidoxy/generator/templates/kotlin/helpers.py
asciidoxy/generator/templates/kotlin/interface.mako
asciidoxy/generator/templates/kotlin/method.mako
asciidoxy/generator/templates/objc/__init__.py
asciidoxy/generator/templates/objc/block.mako
asciidoxy/generator/templates/objc/class.mako
asciidoxy/generator/templates/objc/enum.mako
asciidoxy/generator/templates/objc/helpers.py
asciidoxy-0.8.7.dist-info/LICENSE
asciidoxy-0.8.7.dist-info/METADATA
asciidoxy-0.8.7.dist-info/WHEEL
asciidoxy-0.8.7.dist-info/entry_points.txt
asciidoxy-0.8.7.dist-info/top_level.txt
asciidoxy-0.8.7.dist-info/RECORD
