Metadata-Version: 2.1
Name: asciidoxy
Version: 0.8.7
Summary: AsciiDoxy generates API documentation from Doxygen XML output to AsciiDoc.
Home-page: https://asciidoxy.org
Author: Rob van der Most
Author-email: Rob.vanderMost@TomTom.com
License: Apache 2.0
Project-URL: Documentation, https://asciidoxy.org
Project-URL: Bug Tracker, https://github.com/tomtom-international/asciidoxy/issues
Project-URL: Source Code, https://github.com/tomtom-international/asciidoxy
Keywords: asciidoxy,asciidoc,doxygen,documentation
Classifier: Development Status :: 4 - Beta
Classifier: Intended Audience :: Developers
Classifier: License :: OSI Approved :: Apache Software License
Classifier: Natural Language :: English
Classifier: Operating System :: OS Independent
Classifier: Programming Language :: Python :: 3
Classifier: Programming Language :: Python :: 3.7
Classifier: Programming Language :: Python :: 3.8
Classifier: Programming Language :: Python :: 3.9
Classifier: Programming Language :: Python :: 3.10
Classifier: Programming Language :: Python :: 3.11
Classifier: Topic :: Documentation
Classifier: Topic :: Software Development :: Documentation
License-File: LICENSE
Requires-Dist: mako ~=1.1
Requires-Dist: aiohttp ~=3.6
Requires-Dist: aiodns
Requires-Dist: toml ~=0.10
Requires-Dist: tqdm ~=4.46
Requires-Dist: packaging ~=20.3
Requires-Dist: cchardet ; python_version < "3.11"
Requires-Dist: importlib-resources >=1.4 ; python_version < "3.9"
